{
  "$schema": "https://developer.microsoft.com/json-schemas/fabric/item/report/definition/visualContainer/2.7.0/schema.json",
  "name": "14a2ca32d3a56913ed7e",
  "position": {
    "x": 381.846984416485,
    "y": 195.13827998811584,
    "z": 15000,
    "height": 367.3388429752066,
    "width": 345.12396694214874,
    "tabOrder": 15000
  },
  "visual": {
    "visualType": "clusteredBarChart",
    "query": {
      "queryState": {
        "Category": {
          "projections": [
            {
              "field": {
                "Column": {
                  "Expression": {
                    "SourceRef": {
                      "Entity": "Chat + Agent Interactions (Audit Logs)"
                    }
                  },
                  "Property": "Expertise_Role"
                }
              },
              "queryRef": "Chat + Agent Interactions (Audit Logs).Expertise_Role",
              "nativeQueryRef": "Expertise_Role",
              "active": true
            }
          ]
        },
        "Tooltips": {
          "projections": [
            {
              "field": {
                "Measure": {
                  "Expression": {
                    "SourceRef": {
                      "Entity": "Chat + Agent Interactions (Audit Logs)"
                    }
                  },
                  "Property": "Stage Top Org"
                }
              },
              "queryRef": "Chat + Agent Interactions (Audit Logs).Stage Top Org",
              "nativeQueryRef": "Top Org",
              "displayName": "Top Org"
            }
          ]
        },
        "Y": {
          "projections": [
            {
              "field": {
                "Measure": {
                  "Expression": {
                    "SourceRef": {
                      "Entity": "Chat + Agent Interactions (Audit Logs)"
                    }
                  },
                  "Property": "% of Users in Stage"
                }
              },
              "queryRef": "Chat + Agent Interactions (Audit Logs).% of Users in Stage",
              "nativeQueryRef": "% of Users ",
              "displayName": "% of Users "
            }
          ]
        }
      },
      "sortDefinition": {
        "sort": [
          {
            "field": {
              "Measure": {
                "Expression": {
                  "SourceRef": {
                    "Entity": "Chat + Agent Interactions (Audit Logs)"
                  }
                },
                "Property": "% of Users in Stage"
              }
            },
            "direction": "Descending"
          }
        ],
        "isDefaultSort": true
      }
    },
    "objects": {
      "legend": [
        {
          "properties": {
            "show": {
              "expr": {
                "Literal": {
                  "Value": "false"
                }
              }
            },
            "position": {
              "expr": {
                "Literal": {
                  "Value": "'BottomCenter'"
                }
              }
            },
            "showTitle": {
              "expr": {
                "Literal": {
                  "Value": "false"
                }
              }
            },
            "showGradientLegend": {
              "expr": {
                "Literal": {
                  "Value": "false"
                }
              }
            }
          }
        }
      ],
      "labels": [
        {
          "properties": {
            "show": {
              "expr": {
                "Literal": {
                  "Value": "true"
                }
              }
            },
            "labelPosition": {
              "expr": {
                "Literal": {
                  "Value": "'Auto'"
                }
              }
            },
            "labelOverflow": {
              "expr": {
                "Literal": {
                  "Value": "true"
                }
              }
            },
            "enableBackground": {
              "expr": {
                "Literal": {
                  "Value": "true"
                }
              }
            },
            "backgroundTransparency": {
              "expr": {
                "Literal": {
                  "Value": "42D"
                }
              }
            },
            "fontSize": {
              "expr": {
                "Literal": {
                  "Value": "8D"
                }
              }
            },
            "color": {
              "solid": {
                "color": {
                  "expr": {
                    "ThemeDataColor": {
                      "ColorId": 0,
                      "Percent": 0
                    }
                  }
                }
              }
            },
            "enableDetailDataLabel": {
              "expr": {
                "Literal": {
                  "Value": "true"
                }
              }
            }
          }
        }
      ],
      "categoryAxis": [
        {
          "properties": {
            "labelColor": {
              "solid": {
                "color": {
                  "expr": {
                    "ThemeDataColor": {
                      "ColorId": 0,
                      "Percent": -0.5
                    }
                  }
                }
              }
            }
          }
        }
      ],
      "dataPoint": [
        {
          "properties": {
            "fill": {
              "solid": {
                "color": {
                  "expr": {
                    "FillRule": {
                      "Input": {
                        "Measure": {
                          "Expression": {
                            "SourceRef": {
                              "Entity": "Chat + Agent Interactions (Audit Logs)"
                            }
                          },
                          "Property": "% of Users in Stage"
                        }
                      },
                      "FillRule": {
                        "linearGradient2": {
                          "min": {
                            "color": {
                              "Literal": {
                                "Value": "'#e6e6e6'"
                              }
                            }
                          },
                          "max": {
                            "color": {
                              "Literal": {
                                "Value": "'#055a4f'"
                              }
                            }
                          },
                          "nullColoringStrategy": {
                            "strategy": {
                              "Literal": {
                                "Value": "'asZero'"
                              }
                            }
                          }
                        }
                      }
                    }
                  }
                }
              }
            }
          },
          "selector": {
            "data": [
              {
                "dataViewWildcard": {
                  "matchingOption": 1
                }
              }
            ]
          }
        }
      ],
      "valueAxis": [
        {
          "properties": {
            "start": {
              "expr": {
                "Literal": {
                  "Value": "0D"
                }
              }
            },
            "showAxisTitle": {
              "expr": {
                "Literal": {
                  "Value": "true"
                }
              }
            },
            "titleFontFamily": {
              "expr": {
                "Literal": {
                  "Value": "'wf_standard-font, helvetica, arial, sans-serif'"
                }
              }
            }
          }
        }
      ]
    },
    "visualContainerObjects": {
      "title": [
        {
          "properties": {
            "text": {
              "expr": {
                "Literal": {
                  "Value": "'2. DEVELOPING USERS'"
                }
              }
            },
            "show": {
              "expr": {
                "Literal": {
                  "Value": "true"
                }
              }
            },
            "titleWrap": {
              "expr": {
                "Literal": {
                  "Value": "true"
                }
              }
            },
            "alignment": {
              "expr": {
                "Literal": {
                  "Value": "'center'"
                }
              }
            },
            "fontSize": {
              "expr": {
                "Literal": {
                  "Value": "12D"
                }
              }
            },
            "fontFamily": {
              "expr": {
                "Literal": {
                  "Value": "'''Segoe UI Semibold'', wf_segoe-ui_semibold, helvetica, arial, sans-serif'"
                }
              }
            }
          }
        }
      ],
      "background": [
        {
          "properties": {
            "show": {
              "expr": {
                "Literal": {
                  "Value": "false"
                }
              }
            },
            "color": {
              "solid": {
                "color": {
                  "expr": {
                    "Literal": {
                      "Value": "'#FFFFFF'"
                    }
                  }
                }
              }
            },
            "transparency": {
              "expr": {
                "Literal": {
                  "Value": "0D"
                }
              }
            }
          }
        }
      ],
      "visualTooltip": [
        {
          "properties": {
            "show": {
              "expr": {
                "Literal": {
                  "Value": "true"
                }
              }
            },
            "titleFontColor": {
              "solid": {
                "color": {
                  "expr": {
                    "Literal": {
                      "Value": "'#252423'"
                    }
                  }
                }
              }
            },
            "valueFontColor": {
              "solid": {
                "color": {
                  "expr": {
                    "Literal": {
                      "Value": "'#252423'"
                    }
                  }
                }
              }
            },
            "background": {
              "solid": {
                "color": {
                  "expr": {
                    "Literal": {
                      "Value": "'#FFFFFF'"
                    }
                  }
                }
              }
            }
          }
        }
      ],
      "spacing": [
        {
          "properties": {
            "customizeSpacing": {
              "expr": {
                "Literal": {
                  "Value": "true"
                }
              }
            },
            "verticalSpacing": {
              "expr": {
                "Literal": {
                  "Value": "10D"
                }
              }
            },
            "spaceBelowSubTitle": {
              "expr": {
                "Literal": {
                  "Value": "16D"
                }
              }
            }
          }
        }
      ],
      "subTitle": [
        {
          "properties": {
            "text": {
              "expr": {
                "Literal": {
                  "Value": "'What specialist roles is AI unlocking?'"
                }
              }
            },
            "show": {
              "expr": {
                "Literal": {
                  "Value": "true"
                }
              }
            },
            "alignment": {
              "expr": {
                "Literal": {
                  "Value": "'center'"
                }
              }
            },
            "fontSize": {
              "expr": {
                "Literal": {
                  "Value": "'12'"
                }
              }
            }
          }
        }
      ],
      "padding": [
        {
          "properties": {
            "top": {
              "expr": {
                "Literal": {
                  "Value": "14D"
                }
              }
            },
            "bottom": {
              "expr": {
                "Literal": {
                  "Value": "16D"
                }
              }
            },
            "left": {
              "expr": {
                "Literal": {
                  "Value": "16D"
                }
              }
            },
            "right": {
              "expr": {
                "Literal": {
                  "Value": "16D"
                }
              }
            }
          }
        }
      ],
      "border": [
        {
          "properties": {
            "show": {
              "expr": {
                "Literal": {
                  "Value": "true"
                }
              }
            },
            "color": {
              "solid": {
                "color": {
                  "expr": {
                    "ThemeDataColor": {
                      "ColorId": 3,
                      "Percent": 0
                    }
                  }
                }
              }
            },
            "radius": {
              "expr": {
                "Literal": {
                  "Value": "4D"
                }
              }
            },
            "width": {
              "expr": {
                "Literal": {
                  "Value": "1D"
                }
              }
            }
          }
        }
      ],
      "dropShadow": [
        {
          "properties": {
            "show": {
              "expr": {
                "Literal": {
                  "Value": "false"
                }
              }
            },
            "preset": {
              "expr": {
                "Literal": {
                  "Value": "'Custom'"
                }
              }
            },
            "transparency": {
              "expr": {
                "Literal": {
                  "Value": "86D"
                }
              }
            },
            "shadowSpread": {
              "expr": {
                "Literal": {
                  "Value": "0D"
                }
              }
            },
            "shadowBlur": {
              "expr": {
                "Literal": {
                  "Value": "3D"
                }
              }
            },
            "angle": {
              "expr": {
                "Literal": {
                  "Value": "90D"
                }
              }
            },
            "shadowDistance": {
              "expr": {
                "Literal": {
                  "Value": "1D"
                }
              }
            }
          }
        }
      ],
      "visualHeader": [
        {
          "properties": {
            "transparency": {
              "expr": {
                "Literal": {
                  "Value": "0D"
                }
              }
            }
          }
        }
      ]
    },
    "drillFilterOtherVisuals": true
  },
  "filterConfig": {
    "filters": [
      {
        "name": "527f07994feaf4251a2f",
        "field": {
          "HierarchyLevel": {
            "Expression": {
              "Hierarchy": {
                "Expression": {
                  "SourceRef": {
                    "Entity": "Chat + Agent Interactions (Audit Logs)"
                  }
                },
                "Hierarchy": "Value_Outcome Hierarchy"
              }
            },
            "Level": "Behavior"
          }
        },
        "type": "TopN",
        "howCreated": "User"
      },
      {
        "name": "31fdda1a264490fa487c",
        "field": {
          "Column": {
            "Expression": {
              "SourceRef": {
                "Entity": "Chat + Agent Interactions (Audit Logs)"
              }
            },
            "Property": "User_Stage_Maturity"
          }
        },
        "type": "Categorical",
        "filter": {
          "Version": 2,
          "From": [
            {
              "Name": "c",
              "Entity": "Chat + Agent Interactions (Audit Logs)",
              "Type": 0
            }
          ],
          "Where": [
            {
              "Condition": {
                "In": {
                  "Expressions": [
                    {
                      "Column": {
                        "Expression": {
                          "SourceRef": {
                            "Source": "c"
                          }
                        },
                        "Property": "User_Stage_Maturity"
                      }
                    }
                  ],
                  "Values": [
                    [
                      {
                        "Literal": {
                          "Value": "'2 - Developing'"
                        }
                      }
                    ]
                  ]
                }
              }
            }
          ]
        },
        "howCreated": "User"
      },
      {
        "name": "bcd91adf80a67d3739ea",
        "field": {
          "Column": {
            "Expression": {
              "SourceRef": {
                "Entity": "Chat + Agent Interactions (Audit Logs)"
              }
            },
            "Property": "Value_Type"
          }
        },
        "type": "Categorical",
        "howCreated": "User"
      },
      {
        "name": "1dca5014d50ae80af181",
        "type": "Exclude",
        "filter": {
          "Version": 2,
          "From": [
            {
              "Name": "c",
              "Entity": "Chat + Agent Interactions (Audit Logs)",
              "Type": 0
            }
          ],
          "Where": [
            {
              "Condition": {
                "Not": {
                  "Expression": {
                    "In": {
                      "Expressions": [
                        {
                          "Column": {
                            "Expression": {
                              "SourceRef": {
                                "Source": "c"
                              }
                            },
                            "Property": "Expertise_Role"
                          }
                        }
                      ],
                      "Values": [
                        [
                          {
                            "Literal": {
                              "Value": "null"
                            }
                          }
                        ]
                      ]
                    }
                  }
                }
              }
            }
          ]
        },
        "howCreated": "Exclude"
      }
    ]
  },
  "isHidden": true
}